MANIFEST.in
setup.cfg
setup.py
versiontools_support.py
pytune/__init__.py
pytune/about.py
pytune/askpypathdlg.py
pytune/cakychart.py
pytune/cakychartactionpanel.py
pytune/cakychartpanel.py
pytune/calleespanel.py
pytune/callerspanel.py
pytune/callgraph.py
pytune/filterpanel.py
pytune/historyactionpanel.py
pytune/historypanel.py
pytune/image_path.py
pytune/list_mixin.py
pytune/listctrl.py
pytune/loaded_stats.py
pytune/my_stats.py
pytune/pack_py2exe.py
pytune/pack_unix.py
pytune/panel.py
pytune/profdlg.py
pytune/proportionalsplitter.py
pytune/savedlg.py
pytune/sector.py
pytune/singleton.py
pytune/statsmodel.py
pytune/statspanel.py
pytune/timeitdlg.py
pytune/ui.py
pytune/uicfg.py
pytune/util.py
pytune/viewpanel.py
pytune/vpt.py
pytune.egg-info/PKG-INFO
pytune.egg-info/SOURCES.txt
pytune.egg-info/dependency_links.txt
pytune.egg-info/entry_points.txt
pytune.egg-info/not-zip-safe
pytune.egg-info/top_level.txt
pytune/codectrl/StyledTextCtrl_2.py
pytune/codectrl/__init__.py
pytune/codectrl/codepanel.py
pytune/codectrl/codepanel_mixin.py
pytune/codectrl/codeview.py