Metadata-Version: 1.0
Name: pytune
Version: 0.2.1
Summary: A tool for Python program performence tuning.
Home-page: http://code.google.com/p/visualpytune/
Author: laiyonghao
Author-email: mail@laiyonghao.com
License: apache license 2
Keywords: profile,performence
Platform: UNKNOWN
